MANIFEST.in
setup.py
src/fsqio/__init__.py
src/fsqio.pants.buildgen.spindle.egg-info/PKG-INFO
src/fsqio.pants.buildgen.spindle.egg-info/SOURCES.txt
src/fsqio.pants.buildgen.spindle.egg-info/dependency_links.txt
src/fsqio.pants.buildgen.spindle.egg-info/namespace_packages.txt
src/fsqio.pants.buildgen.spindle.egg-info/requires.txt
src/fsqio.pants.buildgen.spindle.egg-info/top_level.txt
src/fsqio.pants.buildgen.spindle.egg-info/zip-safe
src/fsqio/pants/__init__.py
src/fsqio/pants/buildgen/__init__.py
src/fsqio/pants/buildgen/spindle/__init__.py
src/fsqio/pants/buildgen/spindle/buildgen_spindle.py
src/fsqio/pants/buildgen/spindle/register.py